edc_appconfig/__init__.py
edc_appconfig/apps.py
edc_appconfig/migrations/__init__.py
edc_appconfig/models.py
edc_appconfig/system_checks.py
edc_appconfig/tests/__init__.py
edc_appconfig/tests/models.py
edc_appconfig/tests/tests/__init__.py
edc_appconfig/tests/tests/tests.py
edc_appconfig/tests/urls.py
edc_appconfig-1.0.3.dist-info/licenses/LICENSE
edc_appconfig-1.0.3.dist-info/WHEEL
edc_appconfig-1.0.3.dist-info/METADATA
edc_appconfig-1.0.3.dist-info/RECORD
