Metadata-Version: 2.4
Name: edc-appconfig
Version: 1.0.3
Summary: Custom AppConfig for main app of clinicedc/edc projects
Keywords: AppConfig,Edc,clinical,clinicedc,django,trials
Author: Erik van Widenfelt
Author-email: Erik van Widenfelt <ew2789@gmail.com>
License-Expression: GPL-3.0-or-later
License-File: LICENSE
Classifier: Environment :: Web Environment
Classifier: Framework :: Django
Classifier: Framework :: Django :: 5.1
Classifier: Intended Audience :: Developers
Classifier: Intended Audience :: Science/Research
Classifier: License :: OSI Approved :: GNU General Public License v3 (GPLv3)
Classifier: Operating System :: OS Independent
Classifier: Programming Language :: Python :: 3.12
Requires-Python: >=3.12, <3.14
Project-URL: Homepage, https://github.com/clinicedc/edc-adherence
